cognitive_core/__init__.py
cognitive_core/cli.py
cognitive_core/config.py
cognitive_core/py.typed
cognitive_core/solver.py
cognitive_core/core/__init__.py
cognitive_core/core/types.py
cognitive_core/embeddings/__init__.py
cognitive_core/embeddings/bge.py
cognitive_core/environments/__init__.py
cognitive_core/environments/base.py
cognitive_core/environments/swe.py
cognitive_core/environments/arc/__init__.py
cognitive_core/environments/arc/environment.py
cognitive_core/environments/arc/loader.py
cognitive_core/environments/arc/types.py
cognitive_core/environments/arc/utils.py
cognitive_core/execution/__init__.py
cognitive_core/execution/executor.py
cognitive_core/execution/prompt_formatter.py
cognitive_core/execution/trajectory_builder.py
cognitive_core/experiments/__init__.py
cognitive_core/learning/__init__.py
cognitive_core/learning/analyzer.py
cognitive_core/learning/extractor.py
cognitive_core/learning/hindsight.py
cognitive_core/learning/pipeline.py
cognitive_core/llm/__init__.py
cognitive_core/llm/simple.py
cognitive_core/mcp/__init__.py
cognitive_core/mcp/memory_server.py
cognitive_core/memory/__init__.py
cognitive_core/memory/concepts.py
cognitive_core/memory/experience.py
cognitive_core/memory/storage.py
cognitive_core/memory/strategy_bank.py
cognitive_core/memory/system.py
cognitive_core/memory/primitives/__init__.py
cognitive_core/memory/primitives/arc.py
cognitive_core/memory/primitives/swe.py
cognitive_core/memory/strategies/__init__.py
cognitive_core/memory/strategies/concepts.py
cognitive_core/memory/strategies/experience.py
cognitive_core/memory/strategies/strategy_bank.py
cognitive_core/protocols/__init__.py
cognitive_core/protocols/agent.py
cognitive_core/protocols/embeddings.py
cognitive_core/protocols/environment.py
cognitive_core/protocols/learning.py
cognitive_core/protocols/llm.py
cognitive_core/protocols/memory.py
cognitive_core/protocols/search.py
cognitive_core/protocols/vector_index.py
cognitive_core/search/__init__.py
cognitive_core-0.0.2.dist-info/METADATA
cognitive_core-0.0.2.dist-info/WHEEL
cognitive_core-0.0.2.dist-info/entry_points.txt
cognitive_core-0.0.2.dist-info/RECORD
