Metadata-Version: 2.4
Name: cognitive-core
Version: 0.0.2
Summary: Cognitive Core - A meta-learning framework for learning from agent trajectories
Project-URL: Homepage, https://github.com/alexngai/meta-learning-engine
Project-URL: Repository, https://github.com/alexngai/meta-learning-engine
Author: Alex Ngai
License-Expression: MIT
Keywords: agents,arc-agi,cognitive,meta-learning,software-engineering,trajectories
Classifier: Development Status :: 3 - Alpha
Classifier: Intended Audience :: Developers
Classifier: Intended Audience :: Science/Research
Classifier: License :: OSI Approved :: MIT License
Classifier: Programming Language :: Python :: 3
Classifier: Programming Language :: Python :: 3.10
Classifier: Programming Language :: Python :: 3.11
Classifier: Programming Language :: Python :: 3.12
Classifier: Topic :: Scientific/Engineering :: Artificial Intelligence
Requires-Python: >=3.10
Requires-Dist: numpy>=1.24
Requires-Dist: pydantic>=2.0
Provides-Extra: all
Requires-Dist: arckit>=1.0.1; extra == 'all'
Requires-Dist: chromadb>=0.4; extra == 'all'
Requires-Dist: docker>=7.0.0; extra == 'all'
Requires-Dist: fastmcp>=0.1; extra == 'all'
Requires-Dist: litellm>=1.0; extra == 'all'
Requires-Dist: sentence-transformers>=2.2; extra == 'all'
Requires-Dist: torch>=2.0; extra == 'all'
Provides-Extra: arc
Requires-Dist: arckit>=1.0.1; extra == 'arc'
Provides-Extra: dev
Requires-Dist: mypy>=1.0; extra == 'dev'
Requires-Dist: pytest-asyncio>=0.21; extra == 'dev'
Requires-Dist: pytest-cov>=4.0; extra == 'dev'
Requires-Dist: pytest>=7.0; extra == 'dev'
Requires-Dist: ruff>=0.1; extra == 'dev'
Provides-Extra: embeddings
Requires-Dist: sentence-transformers>=2.2; extra == 'embeddings'
Requires-Dist: torch>=2.0; extra == 'embeddings'
Provides-Extra: llm
Requires-Dist: litellm>=1.0; extra == 'llm'
Provides-Extra: mcp
Requires-Dist: fastmcp>=0.1; extra == 'mcp'
Provides-Extra: swe
Requires-Dist: docker>=7.0.0; extra == 'swe'
Provides-Extra: vector-stores
Requires-Dist: chromadb>=0.4; extra == 'vector-stores'
